gitforge/__init__.py
gitforge/github.py
gitforge/gitlab.py
gitforge/lib/__init__.py
gitforge/lib/args.py
gitforge/lib/color.py
gitforge/lib/git.py
gitforge/lib/github.py
gitforge/lib/gitlab.py
gitforge/lib/utils.py
gitforge-0.2.2.dist-info/LICENSE
gitforge-0.2.2.dist-info/METADATA
gitforge-0.2.2.dist-info/WHEEL
gitforge-0.2.2.dist-info/entry_points.txt
gitforge-0.2.2.dist-info/top_level.txt
gitforge-0.2.2.dist-info/RECORD
