Metadata-Version: 2.1
Name: gitforge
Version: 0.2.2
Summary: Git Forge API Client..
Home-page: https://github.com/tslight/gitforge
Author: Toby Slight
Author-email: tslight@pm.me
Classifier: Programming Language :: Python :: 3
Classifier: License :: OSI Approved :: ISC License (ISCL)
Classifier: Operating System :: OS Independent
License-File: LICENSE
Requires-Dist: cpager
Requires-Dist: cpick
Requires-Dist: pandas
Requires-Dist: requests
